airos/__init__.py
airos/budget.py
airos/core.py
airos/errors.py
airos/fuse.py
airos/medic.py
airos/pricing.py
airos/providers.py
airos/rca.py
airos/sentinel.py
airos/storage.py
airos/strategies.py
airos/adapters/__init__.py
airos/adapters/autogen.py
airos/adapters/base.py
airos/adapters/crewai.py
airos/adapters/langchain.py
airos/adapters/langgraph.py
airos_sdk-0.4.0.dist-info/licenses/LICENSE
airos_sdk-0.4.0.dist-info/METADATA
airos_sdk-0.4.0.dist-info/WHEEL
airos_sdk-0.4.0.dist-info/top_level.txt
airos_sdk-0.4.0.dist-info/RECORD
