Metadata-Version: 2.4
Name: airos-sdk
Version: 0.4.0
Summary: One decorator to make any AI agent reliable. Loop detection, auto-repair, output validation.
Author-email: Simranjeet Singh <simranmultani197@gmail.com>
License-Expression: MIT
Project-URL: Homepage, https://github.com/simranmultani197/AirOs
Project-URL: Documentation, https://github.com/simranmultani197/AirOs#readme
Project-URL: Repository, https://github.com/simranmultani197/AirOs
Project-URL: Issues, https://github.com/simranmultani197/AirOs/issues
Keywords: ai,agents,reliability,llm,langchain,crewai,autogen,langgraph
Classifier: Development Status :: 4 - Beta
Classifier: Intended Audience :: Developers
Classifier: Programming Language :: Python :: 3
Classifier: Programming Language :: Python :: 3.10
Classifier: Programming Language :: Python :: 3.11
Classifier: Programming Language :: Python :: 3.12
Classifier: Programming Language :: Python :: 3.13
Classifier: Topic :: Software Development :: Libraries :: Python Modules
Classifier: Topic :: Scientific/Engineering :: Artificial Intelligence
Requires-Python: >=3.10
License-File: LICENSE
Requires-Dist: pydantic>=2.0.0
Provides-Extra: groq
Requires-Dist: groq; extra == "groq"
Provides-Extra: openai
Requires-Dist: openai>=1.0.0; extra == "openai"
Provides-Extra: anthropic
Requires-Dist: anthropic>=0.18.0; extra == "anthropic"
Provides-Extra: ollama
Requires-Dist: httpx>=0.25.0; extra == "ollama"
Provides-Extra: llm
Requires-Dist: groq; extra == "llm"
Requires-Dist: openai>=1.0.0; extra == "llm"
Requires-Dist: anthropic>=0.18.0; extra == "llm"
Requires-Dist: httpx>=0.25.0; extra == "llm"
Requires-Dist: python-dotenv; extra == "llm"
Requires-Dist: tenacity>=8.2.0; extra == "llm"
Requires-Dist: tiktoken>=0.5.0; extra == "llm"
Provides-Extra: langchain
Requires-Dist: langchain>=0.1.0; extra == "langchain"
Requires-Dist: langchain-core>=0.1.0; extra == "langchain"
Provides-Extra: crewai
Requires-Dist: crewai>=0.1.0; extra == "crewai"
Provides-Extra: langgraph
Requires-Dist: langgraph; extra == "langgraph"
Provides-Extra: postgres
Requires-Dist: psycopg2-binary>=2.9.0; extra == "postgres"
Provides-Extra: dev
Requires-Dist: pytest>=7.4.0; extra == "dev"
Requires-Dist: pytest-cov>=4.1.0; extra == "dev"
Requires-Dist: pytest-asyncio>=0.21.0; extra == "dev"
Requires-Dist: pytest-mock>=3.12.0; extra == "dev"
Requires-Dist: black>=23.0.0; extra == "dev"
Requires-Dist: ruff>=0.1.0; extra == "dev"
Requires-Dist: mypy>=1.7.0; extra == "dev"
Provides-Extra: all
Requires-Dist: airos-sdk[crewai,dev,langchain,langgraph,llm,postgres]; extra == "all"
Dynamic: license-file
